agent_toolkit/__init__.py
iowarp_agent_toolkit-1.0.4.data/data/agent-toolkit-mcp-servers/adios/.gitignore
iowarp_agent_toolkit-1.0.4.data/data/agent-toolkit-mcp-servers/adios/README.md
iowarp_agent_toolkit-1.0.4.data/data/agent-toolkit-mcp-servers/adios/pyproject.toml
iowarp_agent_toolkit-1.0.4.data/data/agent-toolkit-mcp-servers/adios/uv.lock
iowarp_agent_toolkit-1.0.4.data/data/agent-toolkit-mcp-servers/adios/docs/adios_setup.md
iowarp_agent_toolkit-1.0.4.data/data/agent-toolkit-mcp-servers/adios/docs/basic_install.md
iowarp_agent_toolkit-1.0.4.data/data/agent-toolkit-mcp-servers/adios/docs/example_uses.md
iowarp_agent_toolkit-1.0.4.data/data/agent-toolkit-mcp-servers/adios/sample_data/data1.bp/data.0
iowarp_agent_toolkit-1.0.4.data/data/agent-toolkit-mcp-servers/adios/sample_data/data1.bp/md.0
iowarp_agent_toolkit-1.0.4.data/data/agent-toolkit-mcp-servers/adios/sample_data/data1.bp/md.idx
iowarp_agent_toolkit-1.0.4.data/data/agent-toolkit-mcp-servers/adios/sample_data/data1.bp/mmd.0
iowarp_agent_toolkit-1.0.4.data/data/agent-toolkit-mcp-servers/adios/sample_data/data2.bp/data.0
iowarp_agent_toolkit-1.0.4.data/data/agent-toolkit-mcp-servers/adios/sample_data/data2.bp/md.0
iowarp_agent_toolkit-1.0.4.data/data/agent-toolkit-mcp-servers/adios/sample_data/data2.bp/md.idx
iowarp_agent_toolkit-1.0.4.data/data/agent-toolkit-mcp-servers/adios/sample_data/data2.bp/mmd.0
iowarp_agent_toolkit-1.0.4.data/data/agent-toolkit-mcp-servers/adios/sample_data/data3.bp/data.0
iowarp_agent_toolkit-1.0.4.data/data/agent-toolkit-mcp-servers/adios/sample_data/data3.bp/md.0
iowarp_agent_toolkit-1.0.4.data/data/agent-toolkit-mcp-servers/adios/sample_data/data3.bp/md.idx
iowarp_agent_toolkit-1.0.4.data/data/agent-toolkit-mcp-servers/adios/sample_data/data3.bp/mmd.0
iowarp_agent_toolkit-1.0.4.data/data/agent-toolkit-mcp-servers/adios/sample_data/data4.bp/data.0
iowarp_agent_toolkit-1.0.4.data/data/agent-toolkit-mcp-servers/adios/sample_data/data4.bp/md.0
iowarp_agent_toolkit-1.0.4.dist-info/METADATA
iowarp_agent_toolkit-1.0.4.dist-info/WHEEL
iowarp_agent_toolkit-1.0.4.dist-info/entry_points.txt
iowarp_agent_toolkit-1.0.4.dist-info/licenses/LICENSE
iowarp_agent_toolkit-1.0.4.dist-info/RECORD
