Metadata-Version: 2.4
Name: iowarp-agent-toolkit
Version: 1.0.4
Summary: Agent Toolkit - MCP Servers, Clients, and Tools for AI Agents
Project-URL: Homepage, https://github.com/iowarp/agent-toolkit
Project-URL: Repository, https://github.com/iowarp/agent-toolkit
Project-URL: Issues, https://github.com/iowarp/agent-toolkit/issues
Author-email: IoWarp Team - Gnosis Research Center <grc@illinoistech.edu>
License: BSD-3-Clause
License-File: LICENSE
Keywords: ai-agents,hdf5,hpc,llm-tools,mcp,model-context-protocol,parquet,research-tools,scientific-computing,slurm
Classifier: Development Status :: 5 - Production/Stable
Classifier: Intended Audience :: Developers
Classifier: Intended Audience :: Science/Research
Classifier: License :: OSI Approved :: BSD License
Classifier: Operating System :: OS Independent
Classifier: Programming Language :: Python :: 3
Classifier: Programming Language :: Python :: 3.10
Classifier: Programming Language :: Python :: 3.11
Classifier: Programming Language :: Python :: 3.12
Classifier: Topic :: Scientific/Engineering
Classifier: Topic :: Software Development :: Libraries :: Python Modules
Requires-Python: >=3.10
Requires-Dist: click>=8.1.0
